ncatbot_sync/__init__.py
ncatbot_sync/api.py
ncatbot_sync/client.py
ncatbot_sync/config.py
ncatbot_sync/connect.py
ncatbot_sync/flags.py
ncatbot_sync/logger.py
ncatbot_sync/message.py
ncatbot_sync/status.py
ncatbot_sync-0.1.2.dist-info/licenses/LICENSE
ncatbot_sync-0.1.2.dist-info/METADATA
ncatbot_sync-0.1.2.dist-info/WHEEL
ncatbot_sync-0.1.2.dist-info/top_level.txt
ncatbot_sync-0.1.2.dist-info/RECORD
