Metadata-Version: 2.4
Name: ncatbot_sync
Version: 0.1.2
Summary: 完整实现OneBot v11规范并支持Napcat,LLonebot,Lagrange多协议
Home-page: https://github.com/liyihao1110/ncatbot_sync
Author: 木子
Author-email: lyh_02@qq.com
License: MIT
Project-URL: Documentation, https://ncatbot-1.gitbook.io/ncatbot
Project-URL: Source Code, https://github.com/liyihao1110/ncatbot_sync
Project-URL: Bug Tracker, https://github.com/liyihao1110/ncatbot_sync/issues
Classifier: Development Status :: 5 - Production/Stable
Classifier: Intended Audience :: Developers
Classifier: License :: OSI Approved :: MIT License
Classifier: Programming Language :: Python :: 3
Classifier: Programming Language :: Python :: 3.8
Classifier: Programming Language :: Python :: 3.9
Classifier: Programming Language :: Python :: 3.10
Classifier: Programming Language :: Python :: 3.11
Classifier: Operating System :: OS Independent
Requires-Python: >=3.8
License-File: LICENSE
Requires-Dist: websocket-client>=1.8.0
Requires-Dist: PyYAML>=6.0.2
Requires-Dist: colorama>=0.4.6
Provides-Extra: dev
Requires-Dist: pytest>=6.0; extra == "dev"
Requires-Dist: black>=22.3; extra == "dev"
Requires-Dist: mypy>=0.910; extra == "dev"
Provides-Extra: docs
Requires-Dist: sphinx>=4.0; extra == "docs"
Requires-Dist: sphinx-rtd-theme>=1.0; extra == "docs"
Dynamic: author
Dynamic: author-email
Dynamic: classifier
Dynamic: description
Dynamic: description-content-type
Dynamic: home-page
Dynamic: license
Dynamic: license-file
Dynamic: project-url
Dynamic: provides-extra
Dynamic: requires-dist
Dynamic: requires-python
Dynamic: summary
